LICENSE
MANIFEST.in
README.md
requirements.txt
setup.py
mwsessions/__init__.py
mwsessions/defaults.py
mwsessions/event.py
mwsessions/functions.py
mwsessions/heap.py
mwsessions/mwsessions.py
mwsessions/sessionizer.py
mwsessions.egg-info/PKG-INFO
mwsessions.egg-info/SOURCES.txt
mwsessions.egg-info/dependency_links.txt
mwsessions.egg-info/entry_points.txt
mwsessions.egg-info/top_level.txt
mwsessions/tests/__init__.py
mwsessions/tests/test_functions.py
mwsessions/tests/test_sessionizer.py
mwsessions/utilities/__init__.py
mwsessions/utilities/sessionize.py