Metadata-Version: 1.0
Name: mwsessions
Version: 0.0.2
Summary: A set of utilities for group MediaWiki user actions into sessions.
Home-page: http://github.com/mediawiki-utilities/python-mwsessions
Author: Aaron Halfaker
Author-email: aaron.halfaker@gmail.com
License: The MIT License (MIT)
